[
 {
   "ניתן באחרון": "2021-2",
   "courseNumber": "001.2.0003",
   "courseName": "כימיה של המים"
 },
 {
   "ניתן באחרון": "2021-2",
   "courseNumber": "001.2.0004",
   "courseName": "מבוא להידרולוגיה של תווך לא רווי"
 },
 {
   "ניתן באחרון": "2021-2",
   "courseNumber": "001.2.0009",
   "courseName": "פיזיקה של מערכות חיידקים מורכבות"
 },
 {
   "ניתן באחרון": "2021-2",
   "courseNumber": "001.2.0011",
   "courseName": "השלמת תזה"
 },
 {
   "ניתן באחרון": "2021-2",
   "courseNumber": "001.2.0012",
   "courseName": "נושאים נבחרים בכימות איכות מי תהום"
 },
 {
   "ניתן באחרון": "2021-2",
   "courseNumber": "001.2.0015",
   "courseName": "הכנת ואפיון ממברנות"
 },
 {
   "ניתן באחרון": "2021-2",
   "courseNumber": "001.2.0021",
   "courseName": "גישות חדשנות ביומימטית"
 },
 {
   "ניתן באחרון": "2021-2",
   "courseNumber": "001.2.0032",
   "courseName": "כימיה מתקדמת בטכנולוגיות מים"
 },
 {
   "ניתן באחרון": "2021-2",
   "courseNumber": "001.2.0153",
   "courseName": "כתיבת עבודה מדעית"
 },
 {
   "ניתן באחרון": "2021-2",
   "courseNumber": "001.2.0888",
   "courseName": "עמוס-בדיקה-כתה מקוונת"
 },
 {
   "ניתן באחרון": "2021-2",
   "courseNumber": "001.2.1000",
   "courseName": "המשך כתיבת עבודה"
 },
 {
   "ניתן באחרון": "2021-2",
   "courseNumber": "001.2.1011",
   "courseName": "המשך כתיבת עבודה"
 },
 {
   "ניתן באחרון": "2021-2",
   "courseNumber": "001.2.1103",
   "courseName": "מבוא לאקולוגיה באזורים צחיחים"
 },
 {
   "ניתן באחרון": "2021-2",
   "courseNumber": "001.2.1380",
   "courseName": "Genetics and Breeding"
 },
 {
   "ניתן באחרון": "2021-2",
   "courseNumber": "001.2.1381",
   "courseName": "Plant Protection"
 },
 {
   "ניתן באחרון": "2021-2",
   "courseNumber": "001.2.1382",
   "courseName": "Introduction to plant physiology in agriculture"
 },
 {
   "ניתן באחרון": "2021-2",
   "courseNumber": "001.2.1383",
   "courseName": "Soil, Water and Fertilizers"
 },
 {
   "ניתן באחרון": "2021-2",
   "courseNumber": "001.2.1384",
   "courseName": "Organic Agriculture"
 },
 {
   "ניתן באחרון": "2021-2",
   "courseNumber": "001.2.1385",
   "courseName": "Aquaculture"
 },
 {
   "ניתן באחרון": "2021-2",
   "courseNumber": "001.2.2005",
   "courseName": "פיסיולוגיה של הצמח בתנאי עקה"
 },
 {
   "ניתן באחרון": "2021-2",
   "courseNumber": "001.2.2021",
   "courseName": "מחלות דגים"
 },
 {
   "ניתן באחרון": "2021-2",
   "courseNumber": "001.2.2025",
   "courseName": "אבחון מעשי של מחלות דגים (א)"
 },
 {
   "ניתן באחרון": "2021-2",
   "courseNumber": "001.2.2026",
   "courseName": "אבחון מעשי של מחלות דגים (ב)"
 },
 {
   "ניתן באחרון": "2021-2",
   "courseNumber": "001.2.2027",
   "courseName": "אבחון מעשי של מחלות דגים (ג)"
 },
 {
   "ניתן באחרון": "2021-2",
   "courseNumber": "001.2.2028",
   "courseName": "קריאה מודרכת בנושא שימוש יעיל בשאריות מזון תעשיתי בהזנת דגים, בעיקר באזורים צחיחים"
 },
 {
   "ניתן באחרון": "2021-2",
   "courseNumber": "001.2.2035",
   "courseName": "משטרי השקיית גידולים"
 },
 {
   "ניתן באחרון": "2021-2",
   "courseNumber": "001.2.2037",
   "courseName": "קריאה מודרכת בתחושת עקה בצמחים"
 },
 {
   "ניתן באחרון": "2021-2",
   "courseNumber": "001.2.2049",
   "courseName": "פיזיולוגיה, מערכות רביה ושימושים של מיני קקטוס"
 },
 {
   "ניתן באחרון": "2021-2",
   "courseNumber": "001.2.2051",
   "courseName": "קריאה מודרכת במטבוליזם של ליפידים"
 },
 {
   "ניתן באחרון": "2021-2",
   "courseNumber": "001.2.2054",
   "courseName": "קריאה מודרכת: נושאים נבחרים באקופיזיולוגיה של צמחי מדבר"
 },
 {
   "ניתן באחרון": "2021-2",
   "courseNumber": "001.2.2058",
   "courseName": "אסטרטגיות הקיום של צמחי מדבר חד-שנתיים"
 },
 {
   "ניתן באחרון": "2021-2",
   "courseNumber": "001.2.2065",
   "courseName": "פיזיולוגיה ומטבוליזם של הפרי: גנטיקה מול סביבה"
 },
 {
   "ניתן באחרון": "2021-2",
   "courseNumber": "001.2.2066",
   "courseName": "מעבדה במטבולומיקה"
 },
 {
   "ניתן באחרון": "2021-2",
   "courseNumber": "001.2.2067",
   "courseName": "הבנת תהליכים במערכות של מודלים חקלאיים"
 },
 {
   "ניתן באחרון": "2021-2",
   "courseNumber": "001.2.2069",
   "courseName": "מטבוליזם של ליפידים בצמחים ואצות"
 },
 {
   "ניתן באחרון": "2021-2",
   "courseNumber": "001.2.2071",
   "courseName": "תקשורת כימית ומולקולרית בין צמחים לחרקים"
 },
 {
   "ניתן באחרון": "2021-2",
   "courseNumber": "001.2.2073",
   "courseName": "Plant Breeding and Cytogenetics"
 },
 {
   "ניתן באחרון": "2021-2",
   "courseNumber": "001.2.2173",
   "courseName": "קריאה מודרכת בגידול צמחים וציטוגנטיקה"
 },
 {
   "ניתן באחרון": "2021-2",
   "courseNumber": "001.2.2204",
   "courseName": "חקלאות והיבטים סביבתיים במדעי הקרקע"
 },
 {
   "ניתן באחרון": "2021-2",
   "courseNumber": "001.2.2222",
   "courseName": "סמינר מחלקתי א' (שנה ראשונה)"
 },
 {
   "ניתן באחרון": "2021-2",
   "courseNumber": "001.2.2223",
   "courseName": "סמינר מחלקתי א' (שנה שניה)"
 },
 {
   "ניתן באחרון": "2021-2",
   "courseNumber": "001.2.2224",
   "courseName": "סמינר מחלקתי ב' (שנה ראשונה)"
 },
 {
   "ניתן באחרון": "2021-2",
   "courseNumber": "001.2.2225",
   "courseName": "סמינר מחלקתי ב' (שנה שניה)"
 },
 {
   "ניתן באחרון": "2021-2",
   "courseNumber": "001.2.2288",
   "courseName": "קריאה מודרכת בגורמים המשפיעים על התפתחות שורשים במצב שדה"
 },
 {
   "ניתן באחרון": "2021-2",
   "courseNumber": "001.2.2289",
   "courseName": "קריאה מודרכת בגישה מולקולרית ובגישה של ביולוגיה מערכתית במחקר על עמידות של צמחים לעקות"
 },
 {
   "ניתן באחרון": "2021-2",
   "courseNumber": "001.2.2290",
   "courseName": "קריאה מודרכת בנושא מחלות דגים"
 },
 {
   "ניתן באחרון": "2021-2",
   "courseNumber": "001.2.2300",
   "courseName": "קריאה מודרכת על מטבוליזם של צמחים: אותנטי לסינתטי"
 },
 {
   "ניתן באחרון": "2021-2",
   "courseNumber": "001.2.2301",
   "courseName": "קורס קריאה מודרכת בחישוב מדד הצחיחות באמצעות סדרות זמן מטרולוגיות"
 },
 {
   "ניתן באחרון": "2021-2",
   "courseNumber": "001.2.2302",
   "courseName": "קריאה מודרכת באקולוגיה מערכתית וביו-כימיה"
 },
 {
   "ניתן באחרון": "2021-2",
   "courseNumber": "001.2.2666",
   "courseName": "סמינר סטודנטים- שנה ראשונה"
 },
 {
   "ניתן באחרון": "2021-2",
   "courseNumber": "001.2.2667",
   "courseName": "סמינר סטודנטים- שנה שנייה"
 },
 {
   "ניתן באחרון": "2021-2",
   "courseNumber": "001.2.3020",
   "courseName": "אקולוגיה של יחסי צמח ובעלי חיים"
 },
 {
   "ניתן באחרון": "2021-2",
   "courseNumber": "001.2.3034",
   "courseName": "אקולוגיה של הצומח"
 },
 {
   "ניתן באחרון": "2021-2",
   "courseNumber": "001.2.3037",
   "courseName": "הדרכה אישית באבולוציה"
 },
 {
   "ניתן באחרון": "2021-2",
   "courseNumber": "001.2.3041",
   "courseName": "נושאים באקולוגיה"
 },
 {
   "ניתן באחרון": "2021-2",
   "courseNumber": "001.2.3045",
   "courseName": "גנטיקה של שמירת טבע"
 },
 {
   "ניתן באחרון": "2021-2",
   "courseNumber": "001.2.3086",
   "courseName": "אקולוגיה מקרוביאלית מנקודת מבט אקולוגית"
 },
 {
   "ניתן באחרון": "2021-2",
   "courseNumber": "001.2.3089",
   "courseName": "Animal Behavior in Conservation Biology"
 },
 {
   "ניתן באחרון": "2021-2",
   "courseNumber": "001.2.3090",
   "courseName": "Introduction to Molecular Ecology"
 },
 {
   "ניתן באחרון": "2021-2",
   "courseNumber": "001.2.3091",
   "courseName": "נושאים עכשוויים בשימור הטבע הישראלי - סדנה"
 },
 {
   "ניתן באחרון": "2021-2",
   "courseNumber": "001.2.3094",
   "courseName": "מאקרואקולוגיה"
 },
 {
   "ניתן באחרון": "2021-2",
   "courseNumber": "001.2.3135",
   "courseName": "Biophysical Ecology in the Namib Desert: Field Workshop"
 },
 {
   "ניתן באחרון": "2021-2",
   "courseNumber": "001.2.3334",
   "courseName": "מחקר עצמי"
 },
 {
   "ניתן באחרון": "2021-2",
   "courseNumber": "001.2.3344",
   "courseName": "קריאה מודרכת באקולוגיה מולקולרית"
 },
 {
   "ניתן באחרון": "2021-2",
   "courseNumber": "001.2.3355",
   "courseName": "קריאה מודרכת באקולוגיה מיקרוביאלית"
 },
 {
   "ניתן באחרון": "2021-2",
   "courseNumber": "001.2.3388",
   "courseName": "Analysis of Encounter Data from Marked Animal Population"
 },
 {
   "ניתן באחרון": "2021-2",
   "courseNumber": "001.2.4011",
   "courseName": "מכניקה של זורמים לא ניוטוניים"
 },
 {
   "ניתן באחרון": "2021-2",
   "courseNumber": "001.2.4012",
   "courseName": "אלקטרו דיפוזיה של יונים"
 },
 {
   "ניתן באחרון": "2021-2",
   "courseNumber": "001.2.4022",
   "courseName": "תבניות צומח ואקולוגיה מרחבית"
 },
 {
   "ניתן באחרון": "2021-2",
   "courseNumber": "001.2.4024",
   "courseName": "עיבוד דיגיטלי של תמונות לווין"
 },
 {
   "ניתן באחרון": "2021-2",
   "courseNumber": "001.2.4027",
   "courseName": "מבוא לדינמיקה של נוזלים גיאופיסיקלים"
 },
 {
   "ניתן באחרון": "2021-2",
   "courseNumber": "001.2.4031",
   "courseName": "נושאים בהידרודינמיקה ואלקטרודיפוזיה פיסיקליות-כימיות - א"
 },
 {
   "ניתן באחרון": "2021-2",
   "courseNumber": "001.2.4033",
   "courseName": "נושאים בהידרודינמיקה ואלקטורדיפוזיה פיסיקליות-כימיות - ב"
 },
 {
   "ניתן באחרון": "2021-2",
   "courseNumber": "001.2.4034",
   "courseName": "יישום של מתודות סימטריות בבעיות של פיסיקה מתמטית - קורס המשך"
 },
 {
   "ניתן באחרון": "2021-2",
   "courseNumber": "001.2.4036",
   "courseName": "נושאים נבחרים במכניקת זורמים של הסביבה (ב)"
 },
 {
   "ניתן באחרון": "2021-2",
   "courseNumber": "001.2.4046",
   "courseName": "נושאים מתקדמים בהתקנים פוטוולטאים"
 },
 {
   "ניתן באחרון": "2021-2",
   "courseNumber": "001.2.4047",
   "courseName": "מדעי פני שטח ליישומים סביבתיים"
 },
 {
   "ניתן באחרון": "2021-2",
   "courseNumber": "001.2.4048",
   "courseName": "אופטיקה פיזיקלית"
 },
 {
   "ניתן באחרון": "2021-2",
   "courseNumber": "001.2.4049",
   "courseName": "היבטים לא ליניאריים במערכות אלקטרוכימיות"
 },
 {
   "ניתן באחרון": "2021-2",
   "courseNumber": "001.2.4053",
   "courseName": "Thermodynamics of Radiating Systems and the Optics of Solar Cells"
 },
 {
   "ניתן באחרון": "2021-2",
   "courseNumber": "001.2.4056",
   "courseName": "Aeolian Geomorphology"
 },
 {
   "ניתן באחרון": "2021-2",
   "courseNumber": "001.2.4444",
   "courseName": "סמינר מחלקתי א' (שנה ראשונה)"
 },
 {
   "ניתן באחרון": "2021-2",
   "courseNumber": "001.2.4454",
   "courseName": "סמינר מחלקתי ב' (שנה ראשונה)"
 },
 {
   "ניתן באחרון": "2021-2",
   "courseNumber": "001.2.4464",
   "courseName": "סמינר מחלקתי - א' (שנה שניה)"
 },
 {
   "ניתן באחרון": "2021-2",
   "courseNumber": "001.2.4474",
   "courseName": "סמינר מחלקתי ב' (שנה שניה)"
 },
 {
   "ניתן באחרון": "2021-2",
   "courseNumber": "001.2.5004",
   "courseName": "שיטות עבודה בשדה בהידרולוגיה"
 },
 {
   "ניתן באחרון": "2021-2",
   "courseNumber": "001.2.5005",
   "courseName": "שיטות מעבדה בלימודי סביבה"
 },
 {
   "ניתן באחרון": "2021-2",
   "courseNumber": "001.2.5006",
   "courseName": "תהליכי מעבר בקרקע לא רוויה"
 },
 {
   "ניתן באחרון": "2021-2",
   "courseNumber": "001.2.5012",
   "courseName": "תהליכי ביודגרדציה של תרכובת סינתטית אורגנית במים ובקרקע"
 },
 {
   "ניתן באחרון": "2021-2",
   "courseNumber": "001.2.5026",
   "courseName": "טרנפרומציות של ניטרוגין ואיכות הסביבה"
 },
 {
   "ניתן באחרון": "2021-2",
   "courseNumber": "001.2.5034",
   "courseName": "Environmentally Oriented Electrochemistry"
 },
 {
   "ניתן באחרון": "2021-2",
   "courseNumber": "001.2.5038",
   "courseName": "מים ותברואה"
 },
 {
   "ניתן באחרון": "2021-2",
   "courseNumber": "001.2.5040",
   "courseName": "אקולוגיה מקרוביאלית של קרקע"
 },
 {
   "ניתן באחרון": "2021-2",
   "courseNumber": "001.2.5044",
   "courseName": "תהליכים ביוגיאוכימיים במערכות מים עיליים"
 },
 {
   "ניתן באחרון": "2021-2",
   "courseNumber": "001.2.5060",
   "courseName": "תהליכים ביולוגיים לטיפול בשפכים"
 },
 {
   "ניתן באחרון": "2021-2",
   "courseNumber": "001.2.5062",
   "courseName": "סוציולוגיה מיקרוביאלית: מחיידק יחיד לביופילם וביו-עיבוד"
 },
 {
   "ניתן באחרון": "2021-2",
   "courseNumber": "001.2.5065",
   "courseName": "זרימה ואיכות מים בנחלים: תיאוריה ומעשה"
 },
 {
   "ניתן באחרון": "2021-2",
   "courseNumber": "001.2.5067",
   "courseName": "מבוא להידרולוגיה מזהמת"
 },
 {
   "ניתן באחרון": "2021-2",
   "courseNumber": "001.2.5070",
   "courseName": "Practical Data Science and Machine Learning"
 },
 {
   "ניתן באחרון": "2021-2",
   "courseNumber": "001.2.5100",
   "courseName": "מבוא להידרולוגיה של מים עיליים"
 },
 {
   "ניתן באחרון": "2021-2",
   "courseNumber": "001.2.5555",
   "courseName": "סמינר מחלקתי - א' (שנה ראשונה)"
 },
 {
   "ניתן באחרון": "2021-2",
   "courseNumber": "001.2.5556",
   "courseName": "סמינר מחלקתי - א' (שנה שניה)"
 },
 {
   "ניתן באחרון": "2021-2",
   "courseNumber": "001.2.5557",
   "courseName": "סמינר מחלקתי - ב' (שנה ראשונה)"
 },
 {
   "ניתן באחרון": "2021-2",
   "courseNumber": "001.2.5558",
   "courseName": "סמינר מחלקתי ב' (שנה שניה)"
 },
 {
   "ניתן באחרון": "2021-2",
   "courseNumber": "001.2.6002",
   "courseName": "תאוריה ויישומי מערכות מידע גיאוגרפיות (GIS)"
 },
 {
   "ניתן באחרון": "2021-2",
   "courseNumber": "001.2.6063",
   "courseName": "Guidedd Reading Course in Desert Architecture from Antiquity to Modern Vernacular"
 },
 {
   "ניתן באחרון": "2021-2",
   "courseNumber": "001.2.6666",
   "courseName": "סמינר באקולוגיה"
 },
 {
   "ניתן באחרון": "2021-2",
   "courseNumber": "001.2.7779",
   "courseName": "קורסים מלימודים קודמים"
 },
 {
   "ניתן באחרון": "2021-2",
   "courseNumber": "001.2.8109",
   "courseName": "מקורות מים במזרח התיכון"
 },
 {
   "ניתן באחרון": "2021-2",
   "courseNumber": "001.2.8135",
   "courseName": "מבוא למדעי כדור הארץ"
 },
 {
   "ניתן באחרון": "2021-2",
   "courseNumber": "001.2.8136",
   "courseName": "חינוך סביבתי"
 },
 {
   "ניתן באחרון": "2021-2",
   "courseNumber": "001.2.8137",
   "courseName": "פוליטיקה סביבתית"
 },
 {
   "ניתן באחרון": "2021-2",
   "courseNumber": "001.2.8150",
   "courseName": "קונפליקט או שיתוף פעולה? פוליטיקה, כלכלה וסביבה"
 },
 {
   "ניתן באחרון": "2021-2",
   "courseNumber": "001.2.9991",
   "courseName": "כתיבת תיזה - חלק א"
 },
 {
   "ניתן באחרון": "2021-2",
   "courseNumber": "001.2.9992",
   "courseName": "כתיבת תיזה - חלק ב"
 },
 {
   "ניתן באחרון": "2021-2",
   "courseNumber": "001.2.9995",
   "courseName": "סמינר סטודנטים א'"
 },
 {
   "ניתן באחרון": "2021-2",
   "courseNumber": "001.2.9996",
   "courseName": "סמינר סטודנטים ב'"
 }
]